weatherkit/__init__.py
weatherkit/client.py
weatherkit/forecast.py
weatherkit/token.py
pyweatherkit-0.0.4.dist-info/LICENSE
pyweatherkit-0.0.4.dist-info/WHEEL
pyweatherkit-0.0.4.dist-info/METADATA
pyweatherkit-0.0.4.dist-info/RECORD
