Metadata-Version: 2.1
Name: PyWeatherKit
Version: 0.0.4
Summary: A Python wrapper for the WeatherKit API
Keywords: weather,kit,weatherkit,api
Author-email: David Kopec <david@oaksnow.com>
Requires-Python: >=3.11
Requires-Dist: requests >=2.6
Requires-Dist: pyjwt[crypto] >=2.4.0
Project-URL: Home, https://github.com/davecom/PyWeatherKit
